instructx/__init__.py
instructx/client.py
instructx-0.0.1.dist-info/METADATA
instructx-0.0.1.dist-info/WHEEL
instructx-0.0.1.dist-info/RECORD
